LICENSE
r2pyapi/__init__.py
r2pyapi/py.typed
r2pyapi/r2reader.py
r2pyapi/r2seeker.py
r2pyapi/r2surface.py
r2pyapi/r2types.py
r2pyapi/r2writer.py
r2pyapi/utils.py
r2pyapi-0.1.2.dist-info/LICENSE
r2pyapi-0.1.2.dist-info/WHEEL
r2pyapi-0.1.2.dist-info/METADATA
r2pyapi-0.1.2.dist-info/RECORD
