Metadata-Version: 2.1
Name: r2pyapi
Version: 0.1.2
Summary: High level radare2 python API
License: Apache-2.0
Keywords: radare2,scripting
Author: Koh M. Nakagawa
Author-email: tsunekou1019@gmail.com
Requires-Python: >=3.8,<4.0
Classifier: License :: OSI Approved :: Apache Software License
Classifier: Programming Language :: Python :: 3
Classifier: Programming Language :: Python :: 3.8
Requires-Dist: r2pipe (>=1.5.3,<2.0.0)
